queuer/QueueR.py
queuer/__init__.py
QueueR-1.0.0.dist-info/LICENSE
QueueR-1.0.0.dist-info/METADATA
QueueR-1.0.0.dist-info/WHEEL
QueueR-1.0.0.dist-info/top_level.txt
QueueR-1.0.0.dist-info/RECORD
